aspect_sdk/__init__.py
aspect_sdk/client.py
aspect_sdk/client_config.py
aspect_sdk/py.typed
aspect_sdk/_generated/__init__.py
aspect_sdk/_generated/api_client.py
aspect_sdk/_generated/api_response.py
aspect_sdk/_generated/configuration.py
aspect_sdk/_generated/exceptions.py
aspect_sdk/_generated/py.typed
aspect_sdk/_generated/rest.py
aspect_sdk/_generated/api/__init__.py
aspect_sdk/_generated/api/analyze_api.py
aspect_sdk/_generated/api/assets_api.py
aspect_sdk/_generated/api/indexes_api.py
aspect_sdk/_generated/api/search_api.py
aspect_sdk/_generated/api/tasks_api.py
aspect_sdk/_generated/api/users_api.py
aspect_sdk/_generated/models/__init__.py
aspect_sdk/_generated/models/analyze_ask_request.py
aspect_sdk/_generated/models/analyze_ask_response.py
aspect_sdk/_generated/models/analyze_box_coordinate.py
aspect_sdk/_generated/models/analyze_box_request.py
aspect_sdk/_generated/models/analyze_box_response.py
aspect_sdk/_generated/models/analyze_point_coordinate.py
aspect_sdk/_generated/models/analyze_point_request.py
aspect_sdk/_generated/models/analyze_point_response.py
aspect_sdk/_generated/models/asset_create_response.py
aspect_sdk/_generated/models/asset_download_get_response.py
aspect_sdk/_generated/models/asset_get_response.py
aspect_sdk/_generated/models/asset_list_response.py
aspect_sdk/_generated/models/asset_storage_variant.py
aspect_sdk/_generated/models/asset_type.py
aspect_sdk/_generated/models/asset_update_request.py
aspect_sdk/_generated/models/asset_update_response.py
aspect_sdk/_generated/models/core_feature_type.py
aspect_sdk/_generated/models/embed_provider_type.py
aspect_sdk/_generated/models/feature_info.py
aspect_sdk/_generated/models/feature_state.py
aspect_sdk/_generated/models/http_validation_error.py
aspect_sdk/_generated/models/index_create_request.py
aspect_sdk/_generated/models/index_create_response.py
aspect_sdk/_generated/models/index_get_response.py
aspect_sdk/_generated/models/index_list_response.py
aspect_sdk-0.0.6.dist-info/METADATA
aspect_sdk-0.0.6.dist-info/WHEEL
aspect_sdk-0.0.6.dist-info/top_level.txt
aspect_sdk-0.0.6.dist-info/RECORD
