Metadata-Version: 2.4
Name: aspect-sdk
Version: 0.0.6
Summary: Python SDK for Aspect Media Engine API
Author-email: Aspect Team <admin@aspect.com>
License-Expression: MIT
Project-URL: Homepage, https://github.com/aspect/aspect-media-engine
Project-URL: Repository, https://github.com/aspect/aspect-media-engine
Keywords: aspect,media,engine,api,sdk
Requires-Python: >=3.9
Requires-Dist: urllib3<3.0.0,>=2.1.0
Requires-Dist: python-dateutil>=2.8.2
Requires-Dist: pydantic>=2
Requires-Dist: typing-extensions>=4.7.1
Requires-Dist: setuptools>=80.9.0
Requires-Dist: wheel>=0.45.1
Requires-Dist: build>=1.3.0
